{
  "colorVariables": [1, 2, 4, 7, 8],
  "colorThemes": [
    {
      "themeSort": 1,
      "themeMode": "dark",
      "themeName": "2501221",
      "themeColor": {
        "primary": "#212224",
        "secondary": "#0E77FF"
      },
      "themeNav": "type-1",
      "imgQrcode": "qrcode_d",
      "footerLogo": {
        "bb": "white",
        "ub": "white"
      },
      "floatGotop": "white"
    },
    {
      "themeSort": 2,
      "themeMode": "dark",
      "themeName": "2501222",
      "themeColor": {
        "primary": "#3625af",
        "secondary": "#f47aea"
      },
      "themeNav": "type-1",
      "imgQrcode": "qrcode_e",
      "footerLogo": {
        "bb": "white",
        "ub": "white"
      },
      "floatGotop": "white"
    },
    {
      "themeSort": 3,
      "themeMode": "light",
      "themeName": "2501223",
      "themeColor": {
        "primary": "#0ECEFF",
        "secondary": "#FFA81D"
      },
      "themeNav": "type-3",
      "imgQrcode": "qrcode_b",
      "footerLogo": {
        "bb": "black",
        "ub": "black"
      },
      "floatGotop": "black"
    },
    {
      "themeSort": 4,
      "themeMode": "light",
      "themeName": "2501224",
      "themeColor": {
        "primary": "#e6e6e6",
        "secondary": "#e25757"
      },
      "themeNav": "type-3",
      "imgQrcode": "qrcode_e",
      "footerLogo": {
        "bb": "red",
        "ub": "black"
      },
      "floatGotop": "black"
    }
  ]
}
